openbb_oecd/__init__.py
openbb_oecd/models/composite_leading_indicator.py
openbb_oecd/models/consumer_price_index.py
openbb_oecd/models/country_interest_rates.py
openbb_oecd/models/gdp_forecast.py
openbb_oecd/models/gdp_nominal.py
openbb_oecd/models/gdp_real.py
openbb_oecd/models/house_price_index.py
openbb_oecd/models/immediate_interest_rate.py
openbb_oecd/models/long_term_interest_rate.py
openbb_oecd/models/share_price_index.py
openbb_oecd/models/short_term_interest_rate.py
openbb_oecd/models/unemployment.py
openbb_oecd/utils/constants.py
openbb_oecd/utils/helpers.py
openbb_oecd-1.4.1.dist-info/METADATA
openbb_oecd-1.4.1.dist-info/WHEEL
openbb_oecd-1.4.1.dist-info/entry_points.txt
openbb_oecd-1.4.1.dist-info/RECORD
