Metadata-Version: 2.3
Name: openbb-oecd
Version: 1.4.1
Summary: OECD extension for OpenBB
License: AGPL-3.0-only
Author: OpenBB Team
Author-email: hello@openbb.co
Requires-Python: >=3.9.21,<3.13
Classifier: License :: OSI Approved :: GNU Affero General Public License v3
Classifier: Programming Language :: Python :: 3
Classifier: Programming Language :: Python :: 3.10
Classifier: Programming Language :: Python :: 3.11
Classifier: Programming Language :: Python :: 3.12
Requires-Dist: defusedxml (>=0.8.0rc2,<0.9.0)
Requires-Dist: openbb-core (>=1.4.6,<2.0.0)
Requires-Dist: urllib3 (>1.26.16)
